{
  "keyword": "DLTOBJ",
  "description": "Delete Object (DLTOBJ)",
  "parameters": [
    {
      "name": "OBJ",
      "description": "Object",
      "help": "Object (OBJ)\n\nSpecifies the objects which you want to delete and the library or libraries from which the objects are to be deleted.\n\nThis is a required parameter.\n\nQualifier 1: Object\n\nNote: System library names such as library QSYS are allowed, but be very careful about specifying a system library name with an object name of *ALL.\n\nQualifier 2: Library\n\nUser libraries are all libraries with names that do not begin with the letter Q except for the following:\n\nAlthough the following libraries with names that begin with the letter Q are provided by IBM, they typically contain user data that changes frequently. Therefore, these libraries are also considered user libraries:",
      "inputType": "group",
      "required": true,
      "groupKind": "qualified",
      "children": [
        {
          "name": "LIB",
          "description": "Library",
          "help": "指定できる特殊値: *LIBL, *CURLIB, *USRLIBL, *ALL, *ALLUSR",
          "inputType": "text",
          "required": false,
          "defaultValue": "*LIBL",
          "attributes": {
            "characterSet": "upper",
            "maxLength": 10
          },
          "placeholder": "*LIBL"
        },
        {
          "name": "OBJ",
          "description": "Object",
          "help": "指定できる特殊値: *ALL",
          "inputType": "text",
          "required": true,
          "attributes": {
            "characterSet": "upper",
            "maxLength": 10
          },
          "placeholder": "OBJ"
        }
      ],
      "positional": 1,
      "basic": true
    },
    {
      "name": "OBJTYPE",
      "description": "Object type",
      "help": "Object type (OBJTYPE)\n\nSpecifies the type of object which you want to delete.\n\nTo see a complete list of object types when prompting this command, position the cursor on the field for this parameter and press F4 (Prompt). For a description of the object types, see \"Object types\" in the CL topic collection in the Programming category in the IBM i Information Center at http://www.ibm.com/systems/i/infocenter/.\n\nThis is a required parameter.",
      "inputType": "dropdown",
      "required": true,
      "attributes": {
        "characterSet": "upper",
        "restricted": true,
        "maxLength": 10
      },
      "options": [
        {
          "label": "*ALRTBL",
          "value": "*ALRTBL"
        },
        {
          "label": "*AUTL",
          "value": "*AUTL"
        },
        {
          "label": "*BNDDIR",
          "value": "*BNDDIR"
        },
        {
          "label": "*CFGL",
          "value": "*CFGL"
        },
        {
          "label": "*CHTFMT",
          "value": "*CHTFMT"
        },
        {
          "label": "*CLD",
          "value": "*CLD"
        },
        {
          "label": "*CLS",
          "value": "*CLS"
        },
        {
          "label": "*CMD",
          "value": "*CMD"
        },
        {
          "label": "*CNNL",
          "value": "*CNNL"
        },
        {
          "label": "*COSD",
          "value": "*COSD"
        },
        {
          "label": "*CRQD",
          "value": "*CRQD"
        },
        {
          "label": "*CSI",
          "value": "*CSI"
        },
        {
          "label": "*CSPMAP",
          "value": "*CSPMAP"
        },
        {
          "label": "*CSPTBL",
          "value": "*CSPTBL"
        },
        {
          "label": "*CTLD",
          "value": "*CTLD"
        },
        {
          "label": "*DEVD",
          "value": "*DEVD"
        },
        {
          "label": "*DTAARA",
          "value": "*DTAARA"
        },
        {
          "label": "*DTADCT",
          "value": "*DTADCT"
        },
        {
          "label": "*DTAQ",
          "value": "*DTAQ"
        },
        {
          "label": "*EDTD",
          "value": "*EDTD"
        },
        {
          "label": "*FCT",
          "value": "*FCT"
        },
        {
          "label": "*FILE",
          "value": "*FILE"
        },
        {
          "label": "*FNTRSC",
          "value": "*FNTRSC"
        },
        {
          "label": "*FNTTBL",
          "value": "*FNTTBL"
        },
        {
          "label": "*FORMDF",
          "value": "*FORMDF"
        },
        {
          "label": "*FTR",
          "value": "*FTR"
        },
        {
          "label": "*GSS",
          "value": "*GSS"
        },
        {
          "label": "*IGCDCT",
          "value": "*IGCDCT"
        },
        {
          "label": "*IGCSRT",
          "value": "*IGCSRT"
        },
        {
          "label": "*IGCTBL",
          "value": "*IGCTBL"
        },
        {
          "label": "*IMGCLG",
          "value": "*IMGCLG"
        },
        {
          "label": "*IPXD",
          "value": "*IPXD"
        },
        {
          "label": "*JOBD",
          "value": "*JOBD"
        },
        {
          "label": "*JOBQ",
          "value": "*JOBQ"
        },
        {
          "label": "*JRN",
          "value": "*JRN"
        },
        {
          "label": "*JRNRCV",
          "value": "*JRNRCV"
        },
        {
          "label": "*LIB",
          "value": "*LIB"
        },
        {
          "label": "*LIND",
          "value": "*LIND"
        },
        {
          "label": "*LOCALE",
          "value": "*LOCALE"
        },
        {
          "label": "*MEDDFN",
          "value": "*MEDDFN"
        },
        {
          "label": "*MENU",
          "value": "*MENU"
        },
        {
          "label": "*MGTCOL",
          "value": "*MGTCOL"
        },
        {
          "label": "*MODD",
          "value": "*MODD"
        },
        {
          "label": "*MODULE",
          "value": "*MODULE"
        },
        {
          "label": "*MSGF",
          "value": "*MSGF"
        },
        {
          "label": "*MSGQ",
          "value": "*MSGQ"
        },
        {
          "label": "*NODGRP",
          "value": "*NODGRP"
        },
        {
          "label": "*NODL",
          "value": "*NODL"
        },
        {
          "label": "*NTBD",
          "value": "*NTBD"
        },
        {
          "label": "*NWID",
          "value": "*NWID"
        },
        {
          "label": "*NWSCFG",
          "value": "*NWSCFG"
        },
        {
          "label": "*NWSD",
          "value": "*NWSD"
        },
        {
          "label": "*OUTQ",
          "value": "*OUTQ"
        },
        {
          "label": "*OVL",
          "value": "*OVL"
        },
        {
          "label": "*PAGDFN",
          "value": "*PAGDFN"
        },
        {
          "label": "*PAGSEG",
          "value": "*PAGSEG"
        },
        {
          "label": "*PDFMAP",
          "value": "*PDFMAP"
        },
        {
          "label": "*PDG",
          "value": "*PDG"
        },
        {
          "label": "*PGM",
          "value": "*PGM"
        },
        {
          "label": "*PNLGRP",
          "value": "*PNLGRP"
        },
        {
          "label": "*PSFCFG",
          "value": "*PSFCFG"
        },
        {
          "label": "*QMFORM",
          "value": "*QMFORM"
        },
        {
          "label": "*QMQRY",
          "value": "*QMQRY"
        },
        {
          "label": "*QRYDFN",
          "value": "*QRYDFN"
        },
        {
          "label": "*SBSD",
          "value": "*SBSD"
        },
        {
          "label": "*SCHIDX",
          "value": "*SCHIDX"
        },
        {
          "label": "*SPADCT",
          "value": "*SPADCT"
        },
        {
          "label": "*SQLPKG",
          "value": "*SQLPKG"
        },
        {
          "label": "*SQLUDT",
          "value": "*SQLUDT"
        },
        {
          "label": "*SQLXSR",
          "value": "*SQLXSR"
        },
        {
          "label": "*SRVPGM",
          "value": "*SRVPGM"
        },
        {
          "label": "*SSND",
          "value": "*SSND"
        },
        {
          "label": "*TBL",
          "value": "*TBL"
        },
        {
          "label": "*TIMZON",
          "value": "*TIMZON"
        },
        {
          "label": "*USRIDX",
          "value": "*USRIDX"
        },
        {
          "label": "*USRQ",
          "value": "*USRQ"
        },
        {
          "label": "*USRSPC",
          "value": "*USRSPC"
        },
        {
          "label": "*VLDL",
          "value": "*VLDL"
        },
        {
          "label": "*WSCST",
          "value": "*WSCST"
        }
      ],
      "positional": 2,
      "placeholder": "*FILE",
      "basic": true
    },
    {
      "name": "ASPDEV",
      "description": "ASP device",
      "help": "ASP device (ASPDEV)\n\nSpecifies the auxiliary storage pool (ASP) device name where storage is allocated for the library containing the object. If the library resides in an ASP that is not part of the thread's library name space, this parameter must be specified to ensure the correct library is searched. If this parameter is used when the library qualifier specified for the Object (OBJ) parameter is *CURLIB, *LIBL, or *USRLIBL, ASPDEV(*) is the only valid value.\n\nSpecify the name of the primary or secondary ASP device to be searched. The primary or secondary ASP must have been activated (by varying on the ASP device) and have a status of 'Available'. The system ASP (ASP 1) and defined basic user ASPs (ASPs 2-32) will not be searched.\n\nNote: To specify a specific auxiliary storage pool (ASP) device name, you must have use (*USE) authority for each ASP device in the ASP group.\n\n指定できる特殊値: *, *ALLAVL, *CURASPGRP, *SYSBAS",
      "inputType": "text",
      "required": false,
      "defaultValue": "*",
      "attributes": {
        "characterSet": "upper",
        "maxLength": 10
      },
      "placeholder": "*",
      "basic": true
    },
    {
      "name": "RMVMSG",
      "description": "Remove message",
      "help": "Remove message (RMVMSG)\n\nSpecifies whether or not to remove completion and informational messages related to the deletion of objects from the job log. Messages are only removed if the object was successfully deleted. Diagnostic and escape messages are not removed for objects that could not be deleted.",
      "inputType": "dropdown",
      "required": false,
      "defaultValue": "*NO",
      "attributes": {
        "characterSet": "upper",
        "restricted": true
      },
      "options": [
        {
          "label": "*NO",
          "value": "*NO"
        },
        {
          "label": "*YES",
          "value": "*YES"
        }
      ],
      "basic": true
    }
  ],
  "examples": [
    {
      "code": "DLTOBJ OBJ(MYLIB/*ALL) OBJTYPE(*USRSPC) ASPDEV(*) RMVMSG(*NO)"
    },
    {
      "code": "DLTOBJ OBJ(QSYS/TESTLIBXY*) OBJTYPE(*LIB) ASPDEV(*ALLAVL)"
    }
  ],
  "source": {
    "url": "https://www.ibm.com/docs/en/ssw_ibm_i_74/cl/dltobj.htm",
    "version": "IBM i 7.4"
  }
}
