{
  "keyword": "OVRDBF",
  "description": "Override with Data Base File (OVRDBF)",
  "parameters": [
    {
      "name": "FILE",
      "description": "File being overridden",
      "help": "File being overridden (FILE)\n\nSpecifies the file in the using program to which this override command is applied. The specified file must be a database file when *FILE is specified in the Overriding to data base file (TOFILE) parameter. Otherwise, any device file or database file name can be specified.\n\nThis is a required parameter.",
      "inputType": "text",
      "required": true,
      "attributes": {
        "characterSet": "upper",
        "maxLength": 10
      },
      "positional": 1,
      "basic": true,
      "objectKind": "file"
    },
    {
      "name": "TOFILE",
      "description": "Overriding to data base file",
      "help": "Overriding to data base file (TOFILE)\n\nSpecifies the database file that is used instead of the file specified on the File being overridden (FILE) parameter, or, if *FILE is specified, specifies that certain attributes are overridden by parameters specified in this command. The parameters specified on this command override the same parameters specified in the database file, in the program, or in other previously issued OVRDBF commands.\n\nSingle values\n\nQualifier 1: Overriding to data base file\n\nQualifier 2: Library",
      "inputType": "group",
      "required": false,
      "groupKind": "qualified",
      "singleValues": [
        "*FILE"
      ],
      "children": [
        {
          "name": "LIB",
          "description": "Library",
          "help": "指定できる特殊値: *LIBL, *CURLIB",
          "inputType": "text",
          "required": false,
          "defaultValue": "*LIBL",
          "attributes": {
            "characterSet": "upper",
            "maxLength": 10
          },
          "placeholder": "*LIBL"
        },
        {
          "name": "TOFILE",
          "description": "Overriding to data base file",
          "inputType": "text",
          "required": false,
          "attributes": {
            "characterSet": "upper",
            "maxLength": 10
          },
          "defaultValue": "*FILE",
          "placeholder": "*FILE"
        }
      ],
      "positional": 2,
      "basic": true,
      "objectKind": "file"
    },
    {
      "name": "MBR",
      "description": "Overriding member",
      "help": "Overriding member (MBR)\n\nSpecifies the members used within the database file. This parameter is not valid for distributed data management (DDM) files that refer to remote systems other than the System/38 or the AS/400 system.\n\n指定できる特殊値: *FIRST, *LAST, *ALL",
      "inputType": "text",
      "required": false,
      "attributes": {
        "characterSet": "upper",
        "maxLength": 10
      },
      "positional": 3,
      "placeholder": "*FIRST",
      "basic": true
    },
    {
      "name": "POSITION",
      "description": "Starting position in file",
      "help": "Starting position in file (POSITION)\n\nSpecifies the starting position for reading records from the database file. The first record to get can be at the beginning (*START) or at the end (*END) of the file, the nth record in the file (*RRN), or the record indicated by a key field value and one of the key-search values (*KEY, *KEYA, *KEYAE, *KEYB, or *KEYBE). This parameter overrides the value specified in the program, or in other called OVRDBF commands.\n\nNote: This parameter cannot be specified if *ALL was specified previously on the Overriding member (MBR) parameter.\n\nSingle values\n\nElement 1: Retrieve order\n\nElement 2: *RRN-rcd nbr *KEY-nbr key flds\n\nElement 3: *KEY-rec format having key\n\nElement 4: *KEY-key value\n\nFor example, POSITION(*KEY 1 FMT2 X'123F') specifies that:\n\nThe Distributed database programming topic collection in the IBM i Information Center at http://www.ibm.com/systems/i/infocenter/ has more information on the effects of using the POSITION parameter with DDM files.",
      "inputType": "group",
      "required": false,
      "groupKind": "elements",
      "singleValues": [
        "*NONE",
        "*START",
        "*END"
      ],
      "children": [
        {
          "name": "ORDER",
          "description": "Retrieve order",
          "inputType": "dropdown",
          "required": false,
          "attributes": {
            "characterSet": "upper"
          },
          "options": [
            {
              "label": "*NONE",
              "value": "*NONE"
            },
            {
              "label": "*START",
              "value": "*START"
            },
            {
              "label": "*END",
              "value": "*END"
            },
            {
              "label": "*RRN",
              "value": "*RRN"
            },
            {
              "label": "*KEYB",
              "value": "*KEYB"
            },
            {
              "label": "*KEYBE",
              "value": "*KEYBE"
            },
            {
              "label": "*KEY",
              "value": "*KEY"
            },
            {
              "label": "*KEYAE",
              "value": "*KEYAE"
            },
            {
              "label": "*KEYA",
              "value": "*KEYA"
            }
          ],
          "placeholder": "*NONE"
        },
        {
          "name": "NBR",
          "description": "*RRN-rcd nbr *KEY-nbr key flds",
          "inputType": "number",
          "required": false,
          "attributes": {
            "numericOnly": true
          }
        },
        {
          "name": "RCDFMT",
          "description": "*KEY-rec format having key",
          "inputType": "text",
          "required": false,
          "attributes": {
            "characterSet": "upper",
            "maxLength": 10
          }
        },
        {
          "name": "KEYVAL",
          "description": "*KEY-key value",
          "inputType": "text",
          "required": false
        }
      ],
      "basic": true
    },
    {
      "name": "RCDFMTLCK",
      "description": "Record format lock",
      "help": "Record format lock (RCDFMTLCK)\n\nSpecifies the lock state of the named record format while it is used by the program. The lock state indicates how the data associated with each format is locked. The following example shows the lock states that are specified for each record format and the operations allowed to other programs when the lock is in effect:\n\nAn explanation of each lock state is in the CL topic collection in the Programming category in the IBM i Information Center at http://www.ibm.com/systems/i/infocenter/.\n\nFor each record format, specify the record format name, followed by one lock state value. If the lock state specified for the file in an Allocate Object (ALCOBJ) command is more restrictive than the lock state specified in this parameter, this parameter is ignored. Thus, this parameter can only impose a more restrictive lock state on a record format than the lock state specified for the file.\n\nYou can specify 32 values for this parameter.\n\nElement 1: Record format\n\nElement 2: Lock state",
      "inputType": "group",
      "required": false,
      "groupKind": "elements",
      "children": [
        {
          "name": "RCDFMTLCK_RCDFMT",
          "description": "Record format",
          "inputType": "text",
          "required": false,
          "attributes": {
            "characterSet": "upper",
            "maxLength": 10
          }
        },
        {
          "name": "LCKSTATE",
          "description": "Lock state",
          "inputType": "dropdown",
          "required": false,
          "attributes": {
            "characterSet": "upper"
          },
          "options": [
            {
              "label": "*SHRRD",
              "value": "*SHRRD"
            },
            {
              "label": "*SHRNUP",
              "value": "*SHRNUP"
            },
            {
              "label": "*SHRUPD",
              "value": "*SHRUPD"
            },
            {
              "label": "*EXCLRD",
              "value": "*EXCLRD"
            },
            {
              "label": "*EXCL",
              "value": "*EXCL"
            }
          ]
        }
      ],
      "maxOccurrences": 32,
      "basic": true
    },
    {
      "name": "FRCRATIO",
      "description": "Records to force a write",
      "help": "Records to force a write (FRCRATIO)\n\nSpecifies the number of insert, delete, or update operations that can occur on records before those records are forced into auxiliary (permanent) storage. If this physical file is being journaled, either a large number or *NONE should be used. *NONE may cause long synchronization of the journal and physical files. More information on this parameter is in the CL topic collection in the Programming category in the IBM i Information Center at http://www.ibm.com/systems/i/infocenter/, Appendix A. More information on journal management is in the Recovering your system book, SC41-5304.\n\nThis parameter overrides the force-write ratio specified in the database file, in the program, or in other previously issued OVRDBF commands.\n\n指定できる特殊値: *NONE",
      "inputType": "text",
      "required": false,
      "attributes": {
        "characterSet": "upper",
        "numericOnly": true,
        "valueRelation": {
          "relation": "GE",
          "value": "1"
        }
      },
      "placeholder": "*NONE",
      "basic": true
    },
    {
      "name": "FMTSLR",
      "description": "Rcd format selector program",
      "help": "Rcd format selector program (FMTSLR)\n\nSpecifies the record format selection program that is called when a logical file member contains more than one logical record format. The user-written selection program is called when a record is inserted into the database file and a record format name is not included in the high-level language program. More information about the use of format selector programs is in the Database category in the IBM i Information Center at http://www.ibm.com/systems/i/infocenter/. This parameter overrides the value specified in the database file and in other previously issued OVRDBF commands.\n\nA program specified as the format selector program cannot be created with USRPRF(*OWNER) specified in the Create CL Program (CRTCLPGM) command.\n\nNote: This parameter cannot be specified if *ALL was specified previously on the Overriding member (MBR) parameter.\n\nQualifier 1: Rcd format selector program\n\nQualifier 2: Library",
      "inputType": "group",
      "required": false,
      "groupKind": "qualified",
      "children": [
        {
          "name": "FMTSLR_LIB",
          "description": "Library",
          "help": "指定できる特殊値: *LIBL, *CURLIB",
          "inputType": "text",
          "required": false,
          "defaultValue": "*LIBL",
          "attributes": {
            "characterSet": "upper",
            "maxLength": 10
          },
          "placeholder": "*LIBL"
        },
        {
          "name": "FMTSLR",
          "description": "Rcd format selector program",
          "inputType": "text",
          "required": false,
          "attributes": {
            "characterSet": "upper",
            "maxLength": 10
          }
        }
      ],
      "basic": true
    },
    {
      "name": "WAITFILE",
      "description": "Maximum file wait time",
      "help": "Maximum file wait time (WAITFILE)\n\nSpecifies the number of seconds that the program waits for the file resources to be allocated when the file is opened, or the device or session resources to be allocated when an acquire operation is performed to the file. If the file resources cannot be allocated in the specified wait time, an error message is sent to the program.\n\nThis parameter overrides the wait time specified in the database file, in the program, or in other previously issued OVRDBF commands.\n\nMore information on this parameter is in CL topic collection in the Programming category in the IBM i Information Center at http://www.ibm.com/systems/i/infocenter/, Appendix A.\n\n指定できる特殊値: *IMMED, *CLS",
      "inputType": "text",
      "required": false,
      "attributes": {
        "characterSet": "upper",
        "numericOnly": true,
        "valueRelation": {
          "relation": "GE",
          "value": "1"
        }
      },
      "placeholder": "*IMMED",
      "basic": true
    },
    {
      "name": "WAITRCD",
      "description": "Maximum record wait time",
      "help": "Maximum record wait time (WAITRCD)\n\nSpecifies the number of seconds that a program waits for a record to be updated or deleted, or for a record read in the commitment control environment with LCKLVL(*ALL) specified. More information on record locking is in the Database category in the IBM i Information Center at http://www.ibm.com/systems/i/infocenter/. If the record is not allocated in the specified wait time, an error message is sent to the program.\n\nNote: This parameter overrides the record wait time specified in the database file, specified in the program, or in other previously issued OVRDBF commands. The minimum delay for DDM files is 60 seconds. This value may need to be longer than the delay specified for local database files.\n\n指定できる特殊値: *IMMED, *NOMAX",
      "inputType": "text",
      "required": false,
      "attributes": {
        "characterSet": "upper",
        "numericOnly": true,
        "valueRelation": {
          "relation": "GE",
          "value": "1"
        }
      },
      "placeholder": "*IMMED",
      "basic": true
    },
    {
      "name": "REUSEDLT",
      "description": "Reuse deleted records",
      "help": "Reuse deleted records (REUSEDLT)\n\nSpecifies whether the space used by deleted data entries is reclaimed by future insert requests. Entry reuse cannot be done unless the file was created to allow this: REUSEDLT(*YES). This command cannot override reuse of deleted entries from *NO to *YES.",
      "inputType": "dropdown",
      "required": false,
      "attributes": {
        "characterSet": "upper",
        "restricted": true
      },
      "options": [
        {
          "label": "*NO",
          "value": "*NO"
        }
      ],
      "basic": true
    },
    {
      "name": "NBRRCDS",
      "description": "Records retrieved at once",
      "help": "Records retrieved at once (NBRRCDS)\n\nSpecifies the number of records read from auxiliary storage as a unit and written to main storage as a unit. The amount of data actually read is equal to the number of records times the physical record length, not the logical record length.\n\nThis parameter is valid for sequential or random processing and is specified only when the data records are physically located in auxiliary storage in the sequence in which they are processed. This parameter overrides the number of records value specified in the program, or in other previously issued OVRDBF commands.",
      "inputType": "number",
      "required": false,
      "attributes": {
        "numericOnly": true,
        "valueRelation": {
          "relation": "GT",
          "value": "0"
        }
      },
      "basic": true
    },
    {
      "name": "EOFDLY",
      "description": "EOF retry delay in sec",
      "help": "EOF retry delay in sec (EOFDLY)\n\nSpecifies the number of seconds of delay before trying to read additional records when end of file is reached. This delay is used to allow other jobs an opportunity to add records to the file, and have the new records processed without having to start the job again. When the delay time ends, the job is made active, and data management determines whether any new records were added. If no new records were added, the job waits for another time delay without informing the application program. When a number of seconds is given, no end of file occurs on the given database file until an End Job (ENDJOB) command or forced end of data (FEOD) occurs.\n\nNote: This parameter cannot be specified if *ALL was specified previously on the Overriding member (MBR) parameter.\n\nThere are several ways to end a job that is waiting for records due to an EOFDLY. They are:\n\n指定できる特殊値: *NONE",
      "inputType": "text",
      "required": false,
      "attributes": {
        "characterSet": "upper",
        "minValue": 1,
        "maxValue": 99999,
        "numericOnly": true
      },
      "placeholder": "*NONE",
      "basic": true
    },
    {
      "name": "LVLCHK",
      "description": "Record format level check",
      "help": "Record format level check (LVLCHK)\n\nSpecifies whether the level identifiers for the record formats of the database file are checked when the file is opened by a program. For this check, which is done while the member is opened, the system compares the record format identifiers of each record format used by the program with the corresponding identifiers in the database member. Level checking cannot be done unless the program contains the record format identifiers. This command cannot override level checking from *NO to *YES.",
      "inputType": "dropdown",
      "required": false,
      "attributes": {
        "characterSet": "upper",
        "restricted": true
      },
      "options": [
        {
          "label": "*NO",
          "value": "*NO"
        }
      ],
      "basic": true
    },
    {
      "name": "EXPCHK",
      "description": "Check expiration date",
      "help": "Check expiration date (EXPCHK)\n\nSpecifies whether the expiration date of the named member is checked. This date check is valid only on a physical file member. This parameter overrides the value specified in the program, or in other called OVRDBF commands.",
      "inputType": "dropdown",
      "required": false,
      "attributes": {
        "characterSet": "upper",
        "restricted": true
      },
      "options": [
        {
          "label": "*YES",
          "value": "*YES"
        },
        {
          "label": "*NO",
          "value": "*NO"
        }
      ],
      "basic": true
    },
    {
      "name": "INHWRT",
      "description": "Inhibit write",
      "help": "Inhibit write (INHWRT)\n\nSpecifies whether the processed records are written, deleted, or updated in the database file. The inhibit write parameter allows you to test a program without storing the processed records in the database. This parameter overrides the INHWRT parameter in other previously issued OVRDBF commands.\n\nNote: This parameter cannot be specified if *ALL is specified on the Overriding member (MBR) parameter.",
      "inputType": "dropdown",
      "required": false,
      "attributes": {
        "characterSet": "upper",
        "restricted": true
      },
      "options": [
        {
          "label": "*YES",
          "value": "*YES"
        },
        {
          "label": "*NO",
          "value": "*NO"
        }
      ],
      "basic": true
    },
    {
      "name": "SECURE",
      "description": "Secure from other overrides",
      "help": "Secure from other overrides (SECURE)\n\nSpecifies whether this file is safe from the effects of previously called file override commands.",
      "inputType": "dropdown",
      "required": false,
      "defaultValue": "*NO",
      "attributes": {
        "characterSet": "upper",
        "restricted": true
      },
      "options": [
        {
          "label": "*NO",
          "value": "*NO"
        },
        {
          "label": "*YES",
          "value": "*YES"
        }
      ],
      "basic": true
    },
    {
      "name": "OVRSCOPE",
      "description": "Override scope",
      "help": "Override scope (OVRSCOPE)\n\nSpecifies the extent of influence (scope) of the override.",
      "inputType": "dropdown",
      "required": false,
      "defaultValue": "*ACTGRPDFN",
      "attributes": {
        "characterSet": "upper",
        "restricted": true
      },
      "options": [
        {
          "label": "*ACTGRPDFN",
          "value": "*ACTGRPDFN"
        },
        {
          "label": "*CALLLVL",
          "value": "*CALLLVL"
        },
        {
          "label": "*JOB",
          "value": "*JOB"
        }
      ],
      "basic": true
    },
    {
      "name": "SHARE",
      "description": "Share open data path",
      "help": "Share open data path (SHARE)\n\nSpecifies whether the open data path (ODP) is shared with other programs in the same routing step. When an ODP is shared, the programs accessing the file share facilities such as the file status and the buffer.\n\nMore information on shared database files is in the Database category in the IBM i Information Center at http://www.ibm.com/systems/i/infocenter/.",
      "inputType": "dropdown",
      "required": false,
      "attributes": {
        "characterSet": "upper",
        "restricted": true
      },
      "options": [
        {
          "label": "*NO",
          "value": "*NO"
        },
        {
          "label": "*YES",
          "value": "*YES"
        }
      ],
      "basic": true
    },
    {
      "name": "OPNSCOPE",
      "description": "Open scope",
      "help": "Open scope (OPNSCOPE)\n\nSpecifies the extent of influence (scope) of the open operation.",
      "inputType": "dropdown",
      "required": false,
      "attributes": {
        "characterSet": "upper",
        "restricted": true
      },
      "options": [
        {
          "label": "*ACTGRPDFN",
          "value": "*ACTGRPDFN"
        },
        {
          "label": "*JOB",
          "value": "*JOB"
        }
      ],
      "basic": true
    },
    {
      "name": "SEQONLY",
      "description": "Limit to sequential only",
      "help": "Limit to sequential only (SEQONLY)\n\nSpecifies, for database files whose records are processed in sequential order only, whether sequential only processing is used on the file. This parameter also specifies the number of records transferred as a group to or from the database if sequential only processing is used. If a number is not specified, a default number is determined by the system. This parameter is used to improve the performance of programs that process database files in a sequential manner. This parameter overrides the value specified in the program or in other previously issued OVRDBF commands.\n\nFor files opened for input only in a program, the specified number of records is transferred as a group from the database to an internal data management buffer.\n\nFor files opened for output only in a program, a group of records is transferred to the database whenever the internal data management buffer receives the specified number of processed records from the program. For output files, sequential-only processing is valid for physical file members and for logical file members that are based on one physical file member only.\n\nIf SEQONLY(*YES) is specified, and any of the following conditions are true, the SEQONLY parameter is ignored and a message is issued.\n\nNote: Unpredictable results occur when this parameter is used for alternate index files for DDM on a system other than an iSeries or AS/400 system.\n\nSingle values\n\nElement 1: Sequential only\n\nElement 2: Number of records\n\nThe user must ensure that the buffer size specified is always available to the program in the storage pool in which the program is running. The file uses sequential-only processing.\n\nWhile records are in the internal data management buffer, other jobs can make changes to the same records in the database, and the program performing sequential-only input processing does not see the updates. To ensure that no other updating is done to records while they are in the buffer, the Allocate Object (ALCOBJ) command can be used in the program to specify either an *EXCLRD or an *EXCL lock on the file.\n\nIf a program performs sequential-only output processing and does not handle output errors (such as duplicate keys and conversion mapping errors) that may occur when the records in the buffer are written to the database, records in the buffer after the first record in error are not written.\n\nIf the file is opened for output and the value specified in this parameter is not the same as the force write ratio specified for the file, the value used by the system is the smaller of the two; a message stating which value is changed is sent to the user.\n\nWhen processing SEQONLY(*YES) for writing records into a database file, feedback information for each record (such as relative record number) is not always changed. If such feedback information is important, specify SEQONLY(*NO) or SEQONLY(*YES 1).\n\nMore information on sequence-only database files is in the Database category in the IBM i Information Center at http://www.ibm.com/systems/i/infocenter/.",
      "inputType": "group",
      "required": false,
      "groupKind": "elements",
      "singleValues": [
        "*NO"
      ],
      "children": [
        {
          "name": "SEQ",
          "description": "Sequential only",
          "inputType": "dropdown",
          "required": false,
          "attributes": {
            "characterSet": "upper"
          },
          "options": [
            {
              "label": "*NO",
              "value": "*NO"
            },
            {
              "label": "*YES",
              "value": "*YES"
            }
          ],
          "placeholder": "*NO"
        },
        {
          "name": "SEQONLY_NBRRCDS",
          "description": "Number of records",
          "help": "指定できる特殊値: *BUF32KB, *BUF64KB, *BUF128KB, *BUF256KB",
          "inputType": "text",
          "required": false,
          "attributes": {
            "characterSet": "upper"
          }
        }
      ],
      "basic": true
    },
    {
      "name": "DSTDTA",
      "description": "Distributed Data",
      "help": "Distributed Data (DSTDTA)\n\nSpecifies the data retrieval method used for a distributed file. This parameter has no effect if used against a non-distributed file. Other parameters, such as SEQONLY, still affect how the data is retrieved from each system, and this parameter controls how all the data is managed when accessing a distributed file. This parameter overrides the distributed file data retrieval method selected by the system, or specified in other previously issued OVRDBF commands. More information on DSTDTA can be found in the DB2 Multisystem topic collection in the IBM i Information Center at http://www.ibm.com/systems/i/infocenter/.",
      "inputType": "dropdown",
      "required": false,
      "attributes": {
        "characterSet": "upper",
        "restricted": true
      },
      "options": [
        {
          "label": "*BUFFERED",
          "value": "*BUFFERED"
        },
        {
          "label": "*PROTECTED",
          "value": "*PROTECTED"
        },
        {
          "label": "*CURRENT",
          "value": "*CURRENT"
        }
      ],
      "basic": true
    }
  ],
  "examples": [
    {
      "code": "OVRDBF FILE(ORDERSIN) MBR(MONDAY)"
    },
    {
      "code": "OVRDBF FILE(ORDERSIN) SHARE(*YES)"
    },
    {
      "code": "OVRDBF FILE(INPUT) TOFILE(PAYROLL) MBR(MBR1) RCDFMTLCK((EMPDATA *EXCL))"
    }
  ],
  "source": {
    "url": "https://www.ibm.com/docs/en/ssw_ibm_i_74/cl/ovrdbf.htm",
    "version": "IBM i 7.4"
  }
}
