{
  "keyword": "I-SPEC",
  "description": "固定長 I 仕様書（入力仕様書）。",
  "help": "I-SPEC（桁6='I'）でプログラム記述ファイルの入力レコード／フィールドを定義します。I 仕様はレコード識別行（7-41 桁）とフィールド記述行（43-74 桁）の2行種を持ち、本定義は原典の桁位置表を1:1で写像します（行種に応じて該当欄のみ使用）。桁位置は ILE(RPG IV) に従います。現在は外部記述(E 仕様)が一般的で I 仕様の使用は減少しています。",
  "parameters": [
    {
      "name": "FILENAME",
      "description": "ファイル名／データ構造名（7-16 桁）",
      "help": "レコード識別行で入力ファイル名またはデータ構造名を指定します（最大 10 文字）。フィールド記述行では空白。",
      "inputType": "text",
      "required": false,
      "sourceStart": 7,
      "sourceLength": 10,
      "attributes": {
        "characterSet": "upper",
        "maxLength": 10
      },
      "placeholder": "INPUTFILE"
    },
    {
      "name": "LOGICAL",
      "description": "論理関係／標識（17-18 桁）",
      "help": "レコードの論理関係（AND/OR）や標識を指定します。",
      "inputType": "text",
      "required": false,
      "sourceStart": 17,
      "sourceLength": 2,
      "attributes": {
        "characterSet": "upper",
        "maxLength": 2
      },
      "placeholder": "",
      "visibleByDefault": false
    },
    {
      "name": "RECIDIND",
      "description": "レコード識別標識（19-20 桁）",
      "help": "レコードを識別する標識（例 01〜99）を指定します。",
      "inputType": "text",
      "required": false,
      "sourceStart": 19,
      "sourceLength": 2,
      "attributes": {
        "characterSet": "upper",
        "maxLength": 2
      },
      "placeholder": ""
    },
    {
      "name": "RECIDCODE",
      "description": "レコード識別コード（21-41 桁）",
      "help": "レコードを識別するための位置・コード条件を指定します。",
      "inputType": "text",
      "required": false,
      "sourceStart": 21,
      "sourceLength": 21,
      "attributes": {
        "characterSet": "upper",
        "maxLength": 21
      },
      "placeholder": "",
      "visibleByDefault": false
    },
    {
      "name": "FROM",
      "description": "フィールド位置 From（43-46 桁）",
      "help": "フィールド記述行で、フィールドの開始位置を指定します。",
      "inputType": "number",
      "required": false,
      "sourceStart": 43,
      "sourceLength": 4,
      "attributes": {
        "numericOnly": true,
        "maxLength": 4
      },
      "placeholder": ""
    },
    {
      "name": "TO",
      "description": "フィールド位置 To（47-51 桁）",
      "help": "フィールド記述行で、フィールドの終了位置を指定します。",
      "inputType": "number",
      "required": false,
      "sourceStart": 47,
      "sourceLength": 5,
      "attributes": {
        "numericOnly": true,
        "maxLength": 5
      },
      "placeholder": ""
    },
    {
      "name": "DATATYPE",
      "description": "データ・タイプ（52 桁）",
      "help": "フィールドのデータ・タイプ／形式を指定します（例 P=パック10進, B=2進。空白=文字/ゾーン）。",
      "inputType": "text",
      "required": false,
      "sourceStart": 52,
      "sourceLength": 1,
      "attributes": {
        "characterSet": "upper",
        "maxLength": 1
      },
      "placeholder": ""
    },
    {
      "name": "DECPOS",
      "description": "小数点位置／日付形式（53-58 桁）",
      "help": "数値フィールドの小数桁数、または日付フィールドの形式を指定します。",
      "inputType": "text",
      "required": false,
      "sourceStart": 53,
      "sourceLength": 6,
      "attributes": {
        "characterSet": "upper",
        "maxLength": 6
      },
      "placeholder": "",
      "visibleByDefault": false
    },
    {
      "name": "FIELDNAME",
      "description": "フィールド名（59-68 桁）",
      "help": "プログラム内で参照する入力フィールド名を指定します（最大 10 文字）。",
      "inputType": "text",
      "required": false,
      "sourceStart": 59,
      "sourceLength": 10,
      "attributes": {
        "characterSet": "upper",
        "maxLength": 10
      },
      "placeholder": "CUSTNO"
    },
    {
      "name": "CTLLEVEL",
      "description": "制御レベル（69-74 桁）",
      "help": "制御レベル標識（L1〜L9）やマッチング・フィールド等を指定します。",
      "inputType": "text",
      "required": false,
      "sourceStart": 69,
      "sourceLength": 6,
      "attributes": {
        "characterSet": "upper",
        "maxLength": 6
      },
      "placeholder": "",
      "visibleByDefault": false
    },
    {
      "name": "COMMENT",
      "description": "コメント（任意）",
      "help": "81 桁目以降に自由記述できます。",
      "inputType": "text",
      "required": false,
      "sourceStart": 81,
      "sourceLength": 50,
      "attributes": {
        "maxLength": 50
      },
      "placeholder": "",
      "visibleByDefault": false
    }
  ]
}
