{
  "keyword": "DOUNTIL",
  "description": "DO UNTIL (DOUNTIL)",
  "help": "DO UNTIL (DOUNTIL)コマンドは，CLコマンドのグループを1回以上処理します。グループ内のコマンドがすべて処理された後，論理条件が評価されます。\n\n論理式が偽（論理0)であれば，式が偽に評価され続ける限りにおいて，このDO UNTILグループ内のコマンドが処理されます。論理式が真（論理1)に評価されると，関連したENDDOコマンドの次のコマンドに制御権が渡されます。",
  "parameters": [
    {
      "name": "COND",
      "description": "条件",
      "help": "プログラム中の条件およびループを再び処理するかどうかを決定するために評価される論理式を指定します。論理式については，IBM i Information Center(http://www.ibm.com/systems/i/infocenter/)の「プログラミング」カテゴリーの「制御言語(CL)」トピック・コレクションの「論理式」を参照してください。式の中では変数，固定情報，そして%SUBSTRING, %SWITCH,および%BINARY組み込み関数を使用できることに注意してください。\n\nCLモジュールの作成(CRTCLMOD)コマンドまたはバインドCLプログラムの作成(CRTBNDCL)コマンドを使用してCLソースをコンパイルする場合には，ポインターがヌル値かどうかをテストするために，CLポインター変数を特殊値*NULLと比較できます。CLプログラム作成(CRTCLPGM)コマンドを使用してCLソースをコンパイルする場合は，ADDRESS(*NULL)で宣言されていて，変更されていない別のCLポインター変数とCLポインター変数を比較します。\n\nこれは必須パラメーターです。\n\nCL論理変数または論理式の名前を指定してください。",
      "inputType": "text",
      "required": true,
      "positional": 1,
      "placeholder": "&I *GT 10"
    }
  ],
  "threadSafe": true,
  "environment": "バッチ・プログラム (*BPGM) 対話式プログラム (*IPGM)",
  "restrictions": [
    "このコマンドはCLプログラムまたはILE CLプロシージャー内でのみ有効です。",
    "ネストされたDO, DOWHILE, DOUNTIL,およびDOFORコマンドのレベルは，最大で25まで可能です。"
  ],
  "examples": [
    {
      "code": "DOUNTIL   COND('0')"
    }
  ],
  "source": {
    "url": "https://www.ibm.com/docs/ja/ssw_ibm_i_74/cl/dountil.htm",
    "version": "IBM i 7.4",
    "updated": "2021-04-13"
  }
}
